attp_client/__init__.py
attp_client/catalog.py
attp_client/client.py
attp_client/consts.py
attp_client/core/__init__.py
attp_client/core/ack_gate.py
attp_client/core/dispatcher.py
attp_client/core/eventbus.py
attp_client/core/receiver.py
attp_client/core/tool_callbacks.py
attp_client/core/utils/callbacks.py
attp_client/core/utils/executor.py
attp_client/errors/attp_exception.py
attp_client/errors/correlated_rpc_exception.py
attp_client/errors/dead_session.py
attp_client/errors/not_found.py
attp_client/errors/serialization_error.py
attp_client/errors/unauthenticated_error.py
attp_client/inference.py
attp_client/interfaces/catalogs/catalog.py
attp_client/interfaces/catalogs/tools/envelope.py
attp_client/interfaces/catalogs/tools/tool.py
attp_client/interfaces/error.py
attp_client/interfaces/handshake/auth.py
attp_client/interfaces/handshake/hello.py
attp_client/interfaces/handshake/ready.py
attp_client/interfaces/inference/enums/message_data_type.py
attp_client/interfaces/inference/enums/message_emergency_type.py
attp_client/interfaces/inference/enums/message_type.py
attp_client/interfaces/inference/message.py
attp_client/interfaces/inference/tool.py
attp_client/interfaces/objects/agent.py
attp_client/interfaces/objects/chat.py
attp_client/interfaces/route_mappings.py
attp_client/misc/fixed_basemodel.py
attp_client/misc/paginated.py
attp_client/misc/serializable.py
attp_client/objects/agents.py
attp_client/objects/chats.py
attp_client/router.py
attp_client/session.py
attp_client/tools.py
attp_client/types/chatmode.py
attp_client/types/route_mapping.py
attp_client/utils/context_awaiter.py
attp_client/utils/envelopizer.py
attp_client/utils/route_mapper.py
attp_client/utils/serializer.py
attp_client/utils/stream_object.py
attp_client/utils/stream_receiver.py
attp_client/utils/trigger_callable.py
attp_client-0.0.25.dist-info/METADATA
attp_client-0.0.25.dist-info/WHEEL
attp_client-0.0.25.dist-info/RECORD
