Metadata-Version: 2.3
Name: attp-client
Version: 0.0.25
Summary: A python-sdk client for interacting with AgentHub's ATTP protocol (Agent Tool Transport Protocol)
License: MIT
Author: Ascender Team
Requires-Python: >=3.11,<3.14
Classifier: License :: OSI Approved :: MIT License
Classifier: Programming Language :: Python :: 3
Classifier: Programming Language :: Python :: 3.11
Classifier: Programming Language :: Python :: 3.12
Classifier: Programming Language :: Python :: 3.13
Requires-Dist: ascender-framework (>=2.0rc7,<3.0)
Requires-Dist: attp-core (==0.2.4)
Requires-Dist: msgpack (>=1.1.1,<2.0.0)
Requires-Dist: pydantic (>=2.11.7,<3.0.0)
